pynuki/__init__.py
pynuki/bridge.py
pynuki/constants.py
pynuki/device.py
pynuki/exceptions.py
pynuki/lock.py
pynuki/opener.py
pynuki/utils.py
pynuki-1.6.2.dist-info/LICENSE
pynuki-1.6.2.dist-info/METADATA
pynuki-1.6.2.dist-info/WHEEL
pynuki-1.6.2.dist-info/RECORD
