Metadata-Version: 2.1
Name: pynuki
Version: 1.6.2
Summary: Python bindings for nuki.io bridges
Home-page: https://github.com/pschmitt/pynuki
License: GPL-3.0-only
Author: Philipp Schmitt
Author-email: philipp@schmitt.co
Requires-Python: >3.8,<4.0
Classifier: License :: OSI Approved :: GNU General Public License v3 (GPLv3)
Classifier: Programming Language :: Python :: 3
Classifier: Programming Language :: Python :: 3.9
Classifier: Programming Language :: Python :: 3.10
Classifier: Programming Language :: Python :: 3.11
Requires-Dist: pynacl (>=1.5.0,<2.0.0)
Requires-Dist: requests (>=2.27,<3)
Project-URL: Repository, https://github.com/pschmitt/pynuki
